pixelpartitioner/.DS_Store
pixelpartitioner/PixelPartitioner.py
pixelpartitioner/__init__.py
pixelpartitioner/getImages.py
pixelpartitioner/plotPixel.py
pixelpartitioner-1.0.2.dist-info/LICENSE
pixelpartitioner-1.0.2.dist-info/METADATA
pixelpartitioner-1.0.2.dist-info/WHEEL
pixelpartitioner-1.0.2.dist-info/RECORD
