Metadata-Version: 2.1
Name: pixelpartitioner
Version: 1.0.2
Summary: Tools for pixel partitioning, intensity-based segmentation, and visualization.
Home-page: https://pypi.org/project/pixelpartitioner/
Keywords: image analysis,multiplex imaging,single cell analysis
Author: Ajit Johnson Nirmal
Author-email: ajitjohnson.n@gmail.com
Requires-Python: >=3.10,<4.0
Classifier: Development Status :: 5 - Production/Stable
Classifier: Natural Language :: English
Classifier: Operating System :: OS Independent
Classifier: Programming Language :: Python
Classifier: Programming Language :: Python :: 3
Classifier: Programming Language :: Python :: 3.10
Classifier: Programming Language :: Python :: 3.11
Requires-Dist: imagecodecs (>=2024.1.1,<2025.0.0)
Requires-Dist: matplotlib (>=3.8.3,<4.0.0)
Requires-Dist: numpy (>=1.26.4,<2.0.0)
Requires-Dist: pandas (>=2.2.1,<3.0.0)
Requires-Dist: pytest (>=8.0.2,<9.0.0)
Requires-Dist: scikit-image (>=0.22.0,<0.23.0)
Requires-Dist: tifffile (>=2024.2.12,<2025.0.0)
Project-URL: Documentation, https://nirmallab.github.io/pixelpartitioner/
Project-URL: Repository, https://github.com/nirmallab/pixelpartitioner
